[
  {
    "key":0,
    "avatar":"https://images.unsplash.com/photo-1624298357597-fd92dfbec01d?ixlib=rb-1.2.1&ixid=MnwxMjA3fDB8MHxwaG90by1wYWdlfHx8fGVufDB8fHx8&auto=format&fit=crop&w=250&q=80",
    "name":"Olivia Rhye",
    "date":"Dec 30 2023",
    "stime":"09:42 PM",
    "etime":"10:50 PM",
    "status":"Canceled"
  },
  {
    "key":1,
    "avatar":"https://images.unsplash.com/photo-1624298357597-fd92dfbec01d?ixlib=rb-1.2.1&ixid=MnwxMjA3fDB8MHxwaG90by1wYWdlfHx8fGVufDB8fHx8&auto=format&fit=crop&w=250&q=80",
    "name":"Ahmad",
    "date":"Dec 30 2023",
    "stime":"09:42 PM",
    "etime":"10:50 PM",
    "status":"Canceled"
  },
  {
    "key":2,
    "avatar":"https://images.unsplash.com/photo-1624298357597-fd92dfbec01d?ixlib=rb-1.2.1&ixid=MnwxMjA3fDB8MHxwaG90by1wYWdlfHx8fGVufDB8fHx8&auto=format&fit=crop&w=250&q=80",
    "name":"Nasser",
    "date":"Dec 30 2023",
    "stime":"09:42 PM",
    "etime":"10:50 PM",
    "status":"Canceled"
  },
  {
    "key":3,
    "avatar":"https://images.unsplash.com/photo-1624298357597-fd92dfbec01d?ixlib=rb-1.2.1&ixid=MnwxMjA3fDB8MHxwaG90by1wYWdlfHx8fGVufDB8fHx8&auto=format&fit=crop&w=250&q=80",
    "name":"AHMAD",
    "date":"Dec 30 2023",
    "stime":"09:42 PM",
    "etime":"10:50 PM",
    "status":"Canceled"
  },
  {
    "key":4,
    "avatar":"https://images.unsplash.com/photo-1624298357597-fd92dfbec01d?ixlib=rb-1.2.1&ixid=MnwxMjA3fDB8MHxwaG90by1wYWdlfHx8fGVufDB8fHx8&auto=format&fit=crop&w=250&q=80",
    "name":"Olivia Rhye",
    "date":"Dec 30 2023",
    "stime":"09:42 PM",
    "etime":"10:50 PM",
    "status":"Canceled"
  },
  {
    "key":5,
    "avatar":"https://images.unsplash.com/photo-1624298357597-fd92dfbec01d?ixlib=rb-1.2.1&ixid=MnwxMjA3fDB8MHxwaG90by1wYWdlfHx8fGVufDB8fHx8&auto=format&fit=crop&w=250&q=80",
    "name":"Olivia Rhye",
    "date":"Dec 30 2023",
    "stime":"09:42 PM",
    "etime":"10:50 PM",
    "status":"Canceled"
  },
  {
    "key":6,
    "avatar":"https://images.unsplash.com/photo-1624298357597-fd92dfbec01d?ixlib=rb-1.2.1&ixid=MnwxMjA3fDB8MHxwaG90by1wYWdlfHx8fGVufDB8fHx8&auto=format&fit=crop&w=250&q=80",
    "name":"Olivia Rhye",
    "date":"Dec 30 2023",
    "stime":"09:42 PM",
    "etime":"10:50 PM",
    "status":"Canceled"
  },
  {
    "key":7,
    "avatar":"https://images.unsplash.com/photo-1624298357597-fd92dfbec01d?ixlib=rb-1.2.1&ixid=MnwxMjA3fDB8MHxwaG90by1wYWdlfHx8fGVufDB8fHx8&auto=format&fit=crop&w=250&q=80",
    "name":"Zlivia Rhye",
    "date":"Dec 30 2023",
    "stime":"09:42 PM",
    "etime":"10:50 PM",
    "status":"Canceled"
  },
  {
    "key":8,
    "avatar":"https://images.unsplash.com/photo-1624298357597-fd92dfbec01d?ixlib=rb-1.2.1&ixid=MnwxMjA3fDB8MHxwaG90by1wYWdlfHx8fGVufDB8fHx8&auto=format&fit=crop&w=250&q=80",
    "name":"Olivia Rhye",
    "date":"Dec 30 2023",
    "stime":"09:42 PM",
    "etime":"10:50 PM",
    "status":"Canceled"
  },
  {
    "key":9,
    "avatar":"https://images.unsplash.com/photo-1624298357597-fd92dfbec01d?ixlib=rb-1.2.1&ixid=MnwxMjA3fDB8MHxwaG90by1wYWdlfHx8fGVufDB8fHx8&auto=format&fit=crop&w=250&q=80",
    "name":"Olivia Rhye",
    "date":"Dec 30 2023",
    "stime":"09:42 PM",
    "etime":"10:50 PM",
    "status":"Canceled"
  },
  {
    "key":10,
    "avatar":"https://images.unsplash.com/photo-1624298357597-fd92dfbec01d?ixlib=rb-1.2.1&ixid=MnwxMjA3fDB8MHxwaG90by1wYWdlfHx8fGVufDB8fHx8&auto=format&fit=crop&w=250&q=80",
    "name":"Baraa",
    "date":"Dec 30 2023",
    "stime":"09:42 PM",
    "etime":"10:50 PM",
    "status":"Canceled"
  },
  {
    "key":11,
    "avatar":"https://images.unsplash.com/photo-1624298357597-fd92dfbec01d?ixlib=rb-1.2.1&ixid=MnwxMjA3fDB8MHxwaG90by1wYWdlfHx8fGVufDB8fHx8&auto=format&fit=crop&w=250&q=80",
    "name":"Olivia Rhye",
    "date":"Dec 30 2023",
    "stime":"09:42 PM",
    "etime":"10:50 PM",
    "status":"Canceled"
  },
  {
    "key":12,
    "avatar":"https://images.unsplash.com/photo-1624298357597-fd92dfbec01d?ixlib=rb-1.2.1&ixid=MnwxMjA3fDB8MHxwaG90by1wYWdlfHx8fGVufDB8fHx8&auto=format&fit=crop&w=250&q=80",
    "name":"Olivia Rhye",
    "date":"Dec 30 2023",
    "stime":"09:42 PM",
    "etime":"10:50 PM",
    "status":"Canceled"
  },
  {
    "key":13,
    "avatar":"https://images.unsplash.com/photo-1624298357597-fd92dfbec01d?ixlib=rb-1.2.1&ixid=MnwxMjA3fDB8MHxwaG90by1wYWdlfHx8fGVufDB8fHx8&auto=format&fit=crop&w=250&q=80",
    "name":"Olivia Rhye",
    "date":"Dec 30 2023",
    "stime":"09:42 PM",
    "etime":"10:50 PM",
    "status":"Canceled"
  },
  {
    "key":14,
    "avatar":"https://images.unsplash.com/photo-1624298357597-fd92dfbec01d?ixlib=rb-1.2.1&ixid=MnwxMjA3fDB8MHxwaG90by1wYWdlfHx8fGVufDB8fHx8&auto=format&fit=crop&w=250&q=80",
    "name":"Olivia Rhye",
    "date":"Dec 30 2023",
    "stime":"09:42 PM",
    "etime":"10:50 PM",
    "status":"Canceled"
  },
  {
    "key":15,
    "avatar":"https://images.unsplash.com/photo-1624298357597-fd92dfbec01d?ixlib=rb-1.2.1&ixid=MnwxMjA3fDB8MHxwaG90by1wYWdlfHx8fGVufDB8fHx8&auto=format&fit=crop&w=250&q=80",
    "name":"Olivia Rhye",
    "date":"Dec 30 2023",
    "stime":"09:42 PM",
    "etime":"10:50 PM",
    "status":"Canceled"
  },
  {
    "key":16,
    "avatar":"https://images.unsplash.com/photo-1624298357597-fd92dfbec01d?ixlib=rb-1.2.1&ixid=MnwxMjA3fDB8MHxwaG90by1wYWdlfHx8fGVufDB8fHx8&auto=format&fit=crop&w=250&q=80",
    "name":"Olivia Rhye",
    "date":"Dec 30 2023",
    "stime":"09:42 PM",
    "etime":"10:50 PM",
    "status":"Canceled"
  },
  {
    "key":17,
    "avatar":"https://images.unsplash.com/photo-1624298357597-fd92dfbec01d?ixlib=rb-1.2.1&ixid=MnwxMjA3fDB8MHxwaG90by1wYWdlfHx8fGVufDB8fHx8&auto=format&fit=crop&w=250&q=80",
    "name":"Olivia Rhye",
    "date":"Dec 30 2023",
    "stime":"09:42 PM",
    "etime":"10:50 PM",
    "status":"Canceled"
  },
  {
    "key":18,
    "avatar":"https://images.unsplash.com/photo-1624298357597-fd92dfbec01d?ixlib=rb-1.2.1&ixid=MnwxMjA3fDB8MHxwaG90by1wYWdlfHx8fGVufDB8fHx8&auto=format&fit=crop&w=250&q=80",
    "name":"Olivia Rhye",
    "date":"Dec 30 2023",
    "stime":"09:42 PM",
    "etime":"10:50 PM",
    "status":"Canceled"
  },
  {
    "key":19,
    "avatar":"https://images.unsplash.com/photo-1624298357597-fd92dfbec01d?ixlib=rb-1.2.1&ixid=MnwxMjA3fDB8MHxwaG90by1wYWdlfHx8fGVufDB8fHx8&auto=format&fit=crop&w=250&q=80",
    "name":"Olivia Rhye",
    "date":"Dec 30 2023",
    "stime":"09:42 PM",
    "etime":"10:50 PM",
    "status":"Canceled"
  },
  {
    "key":20,
    "avatar":"https://images.unsplash.com/photo-1624298357597-fd92dfbec01d?ixlib=rb-1.2.1&ixid=MnwxMjA3fDB8MHxwaG90by1wYWdlfHx8fGVufDB8fHx8&auto=format&fit=crop&w=250&q=80",
    "name":"Olivia Rhye",
    "date":"Dec 30 2023",
    "stime":"09:42 PM",
    "etime":"10:50 PM",
    "status":"Canceled"
  },
  {
    "key":21,
    "avatar":"https://images.unsplash.com/photo-1624298357597-fd92dfbec01d?ixlib=rb-1.2.1&ixid=MnwxMjA3fDB8MHxwaG90by1wYWdlfHx8fGVufDB8fHx8&auto=format&fit=crop&w=250&q=80",
    "name":"Olivia Rhye",
    "date":"Dec 30 2023",
    "stime":"09:42 PM",
    "etime":"10:50 PM",
    "status":"Canceled"
  },
  {
    "key":22,
    "avatar":"https://images.unsplash.com/photo-1624298357597-fd92dfbec01d?ixlib=rb-1.2.1&ixid=MnwxMjA3fDB8MHxwaG90by1wYWdlfHx8fGVufDB8fHx8&auto=format&fit=crop&w=250&q=80",
    "name":"Olivia Rhye",
    "date":"Dec 30 2023",
    "stime":"09:42 PM",
    "etime":"10:50 PM",
    "status":"Canceled"
  },
  {
    "key":23,
    "avatar":"https://images.unsplash.com/photo-1624298357597-fd92dfbec01d?ixlib=rb-1.2.1&ixid=MnwxMjA3fDB8MHxwaG90by1wYWdlfHx8fGVufDB8fHx8&auto=format&fit=crop&w=250&q=80",
    "name":"Ali Rhye",
    "date":"Dec 30 2023",
    "stime":"09:42 PM",
    "etime":"10:50 PM",
    "status":"Canceled"
  },
  {
    "key":24,
    "avatar":"https://images.unsplash.com/photo-1624298357597-fd92dfbec01d?ixlib=rb-1.2.1&ixid=MnwxMjA3fDB8MHxwaG90by1wYWdlfHx8fGVufDB8fHx8&auto=format&fit=crop&w=250&q=80",
    "name":"Olivia Rhye",
    "date":"Dec 30 2023",
    "stime":"09:42 PM",
    "etime":"10:50 PM",
    "status":"Canceled"
  }
]